{
    "version": "1.6.1",
    "architecture": {
        "64bit": {
            "url": "https://github.com/auth0/auth0-cli/releases/download/v1.6.1/auth0-cli_1.6.1_Windows_x86_64.zip",
            "bin": [
                "auth0.exe"
            ],
            "hash": "3e1b089b671b5c6fe258c8e23f7b468e5d03fd82c50df0acf976e681cf9a85a9"
        },
        "arm64": {
            "url": "https://github.com/auth0/auth0-cli/releases/download/v1.6.1/auth0-cli_1.6.1_Windows_arm64.zip",
            "bin": [
                "auth0.exe"
            ],
            "hash": "69664595de983f1e36939f52e3e29a61b333d21d2792cbbcd28af4a3d7d88d49"
        }
    },
    "homepage": "https://auth0.github.io/auth0-cli",
    "license": "MIT",
    "description": "Build, manage and test your Auth0 integrations from the command line",
    "post_install": [
        "Write-Host 'Thanks for installing the Auth0 CLI'"
    ]
}
