{
    "version": "0.12.0",
    "architecture": {
        "64bit": {
            "url": "https://github.com/auth0/auth0-cli/releases/download/v0.12.0/auth0-cli_0.12.0_Windows_x86_64.zip",
            "bin": [
                "auth0.exe"
            ],
            "hash": "206dfd810ecd518bd8b71e36cfc0e535825d8c3409742f1eaf8da5a20a9f3e2a"
        }
    },
    "homepage": "https://auth0.github.io/auth0-cli",
    "license": "MIT",
    "description": "Auth0 command-line tool to supercharge your developer workflow",
    "post_install": [
        "Write-Host 'Thanks for installing the Auth0 CLI'"
    ]
}