{
    "version": "1.27.1",
    "architecture": {
        "64bit": {
            "url": "https://github.com/auth0/auth0-cli/releases/download/v1.27.1/auth0-cli_1.27.1_Windows_x86_64.zip",
            "bin": [
                "auth0.exe"
            ],
            "hash": "3fb549dbd5ad94b1d2b728bf843b582a955d176b4ebb5a06c0849e0c5bf01175"
        },
        "arm64": {
            "url": "https://github.com/auth0/auth0-cli/releases/download/v1.27.1/auth0-cli_1.27.1_Windows_arm64.zip",
            "bin": [
                "auth0.exe"
            ],
            "hash": "d5acfc066801ecb05179ea68314d38822d503729c9a252b9f042ff52100cd8f1"
        }
    },
    "homepage": "https://auth0.github.io/auth0-cli",
    "license": "MIT",
    "description": "Build, manage and test your Auth0 integrations from the command line",
    "post_install": [
        "Write-Host 'Thanks for installing the Auth0 CLI'"
    ]
}