{
    "version": "0.7.0",
    "architecture": {
        "64bit": {
            "url": "https://github.com/auth0/auth0-cli/releases/download/v0.7.0/auth0-cli_0.7.0_Windows_x86_64.zip",
            "bin": [
                "auth0.exe"
            ],
            "hash": "c15c97d3249f94dc8258782daf8b77189c75e5ebf5a69ac1d854bf7856467acf"
        }
    },
    "homepage": "https://github.com/auth0/auth0-cli",
    "license": "MIT",
    "description": "Supercharge your developer workflow.",
    "post_install": [
        "Write-Host 'Thanks for installing the Auth0 CLI'"
    ]
}